recipientgsheets.py
recipientgsheets-0.0.5.dist-info/WHEEL
recipientgsheets-0.0.5.dist-info/METADATA
recipientgsheets-0.0.5.dist-info/RECORD
