Metadata-Version: 2.1
Name: recipientgsheets
Version: 0.0.5
Summary: Модуль, который позволяет использовать данные из Google Таблицы, а также перевести её в csv файл
Author: DaniEruDai
Requires-Python: >=3.10,<4.0
Classifier: Programming Language :: Python :: 3
Classifier: Programming Language :: Python :: 3.10
Requires-Dist: pandas (==1.4.4)
